<DOMSymbolItem xmlns:xsi="http://www.w3.org/2001/XMLSchema-instance" xmlns="http://ns.adobe.com/xfl/2008/" name="Spinner/clock" itemID="540572e4-000000f8" lastModified="1409643484">
  <timeline>
    <DOMTimeline name="clock" currentFrame="23">
      <layers>
        <DOMLayer name="Layer 1" color="#4F80FF" current="true" isSelected="true">
          <frames>
            <DOMFrame index="0" keyMode="9728">
              <elements>
                <DOMBitmapInstance libraryItemName="Spinner/b0.png">
                  <matrix>
                    <Matrix tx="-60" ty="-60"/>
                  </matrix>
                </DOMBitmapInstance>
              </elements>
            </DOMFrame>
            <DOMFrame index="1" keyMode="9728">
              <elements>
                <DOMBitmapInstance libraryItemName="Spinner/b1.png">
                  <matrix>
                    <Matrix tx="-60" ty="-60"/>
                  </matrix>
                </DOMBitmapInstance>
              </elements>
            </DOMFrame>
            <DOMFrame index="2" keyMode="9728">
              <elements>
                <DOMBitmapInstance libraryItemName="Spinner/b2.png">
                  <matrix>
                    <Matrix tx="-60" ty="-60"/>
                  </matrix>
                </DOMBitmapInstance>
              </elements>
            </DOMFrame>
            <DOMFrame index="3" keyMode="9728">
              <elements>
                <DOMBitmapInstance libraryItemName="Spinner/b3.png">
                  <matrix>
                    <Matrix tx="-60" ty="-60"/>
                  </matrix>
                </DOMBitmapInstance>
              </elements>
            </DOMFrame>
            <DOMFrame index="4" keyMode="9728">
              <elements>
                <DOMBitmapInstance libraryItemName="Spinner/b4.png">
                  <matrix>
                    <Matrix tx="-60" ty="-60"/>
                  </matrix>
                </DOMBitmapInstance>
              </elements>
            </DOMFrame>
            <DOMFrame index="5" keyMode="9728">
              <elements>
                <DOMBitmapInstance libraryItemName="Spinner/b5.png">
                  <matrix>
                    <Matrix tx="-60" ty="-60"/>
                  </matrix>
                </DOMBitmapInstance>
              </elements>
            </DOMFrame>
            <DOMFrame index="6" keyMode="9728">
              <elements>
                <DOMBitmapInstance libraryItemName="Spinner/b6.png">
                  <matrix>
                    <Matrix tx="-60" ty="-60"/>
                  </matrix>
                </DOMBitmapInstance>
              </elements>
            </DOMFrame>
            <DOMFrame index="7" keyMode="9728">
              <elements>
                <DOMBitmapInstance libraryItemName="Spinner/b7.png">
                  <matrix>
                    <Matrix tx="-60" ty="-60"/>
                  </matrix>
                </DOMBitmapInstance>
              </elements>
            </DOMFrame>
            <DOMFrame index="8" keyMode="9728">
              <elements>
                <DOMBitmapInstance libraryItemName="Spinner/b8.png">
                  <matrix>
                    <Matrix tx="-60" ty="-60"/>
                  </matrix>
                </DOMBitmapInstance>
              </elements>
            </DOMFrame>
            <DOMFrame index="9" keyMode="9728">
              <elements>
                <DOMBitmapInstance libraryItemName="Spinner/b9.png">
                  <matrix>
                    <Matrix tx="-60" ty="-60"/>
                  </matrix>
                </DOMBitmapInstance>
              </elements>
            </DOMFrame>
            <DOMFrame index="10" keyMode="9728">
              <elements>
                <DOMBitmapInstance libraryItemName="Spinner/b10.png">
                  <matrix>
                    <Matrix tx="-60" ty="-60"/>
                  </matrix>
                </DOMBitmapInstance>
              </elements>
            </DOMFrame>
            <DOMFrame index="11" keyMode="9728">
              <elements>
                <DOMBitmapInstance libraryItemName="Spinner/b11.png">
                  <matrix>
                    <Matrix tx="-60" ty="-60"/>
                  </matrix>
                </DOMBitmapInstance>
              </elements>
            </DOMFrame>
            <DOMFrame index="12" keyMode="9728">
              <elements>
                <DOMBitmapInstance libraryItemName="Spinner/b12.png">
                  <matrix>
                    <Matrix tx="-60" ty="-60"/>
                  </matrix>
                </DOMBitmapInstance>
              </elements>
            </DOMFrame>
            <DOMFrame index="13" keyMode="9728">
              <elements>
                <DOMBitmapInstance libraryItemName="Spinner/b13.png">
                  <matrix>
                    <Matrix tx="-60" ty="-60"/>
                  </matrix>
                </DOMBitmapInstance>
              </elements>
            </DOMFrame>
            <DOMFrame index="14" keyMode="9728">
              <elements>
                <DOMBitmapInstance libraryItemName="Spinner/b14.png">
                  <matrix>
                    <Matrix tx="-60" ty="-60"/>
                  </matrix>
                </DOMBitmapInstance>
              </elements>
            </DOMFrame>
            <DOMFrame index="15" keyMode="9728">
              <elements>
                <DOMBitmapInstance libraryItemName="Spinner/b15.png">
                  <matrix>
                    <Matrix tx="-60" ty="-60"/>
                  </matrix>
                </DOMBitmapInstance>
              </elements>
            </DOMFrame>
            <DOMFrame index="16" keyMode="9728">
              <elements>
                <DOMBitmapInstance libraryItemName="Spinner/b16.png">
                  <matrix>
                    <Matrix tx="-60" ty="-60"/>
                  </matrix>
                </DOMBitmapInstance>
              </elements>
            </DOMFrame>
            <DOMFrame index="17" keyMode="9728">
              <elements>
                <DOMBitmapInstance libraryItemName="Spinner/b17.png">
                  <matrix>
                    <Matrix tx="-60" ty="-60"/>
                  </matrix>
                </DOMBitmapInstance>
              </elements>
            </DOMFrame>
            <DOMFrame index="18" keyMode="9728">
              <elements>
                <DOMBitmapInstance libraryItemName="Spinner/b18.png">
                  <matrix>
                    <Matrix tx="-60" ty="-60"/>
                  </matrix>
                </DOMBitmapInstance>
              </elements>
            </DOMFrame>
            <DOMFrame index="19" keyMode="9728">
              <elements>
                <DOMBitmapInstance libraryItemName="Spinner/b19.png">
                  <matrix>
                    <Matrix tx="-60" ty="-60"/>
                  </matrix>
                </DOMBitmapInstance>
              </elements>
            </DOMFrame>
            <DOMFrame index="20" keyMode="9728">
              <elements>
                <DOMBitmapInstance libraryItemName="Spinner/b20.png">
                  <matrix>
                    <Matrix tx="-60" ty="-60"/>
                  </matrix>
                </DOMBitmapInstance>
              </elements>
            </DOMFrame>
            <DOMFrame index="21" keyMode="9728">
              <elements>
                <DOMBitmapInstance libraryItemName="Spinner/b21.png">
                  <matrix>
                    <Matrix tx="-60" ty="-60"/>
                  </matrix>
                </DOMBitmapInstance>
              </elements>
            </DOMFrame>
            <DOMFrame index="22" keyMode="9728">
              <elements>
                <DOMBitmapInstance libraryItemName="Spinner/b22.png">
                  <matrix>
                    <Matrix tx="-60" ty="-60"/>
                  </matrix>
                </DOMBitmapInstance>
              </elements>
            </DOMFrame>
            <DOMFrame index="23" keyMode="9728">
              <elements>
                <DOMBitmapInstance selected="true" libraryItemName="Spinner/b23.png">
                  <matrix>
                    <Matrix tx="-60" ty="-60"/>
                  </matrix>
                </DOMBitmapInstance>
              </elements>
            </DOMFrame>
          </frames>
        </DOMLayer>
      </layers>
    </DOMTimeline>
  </timeline>
</DOMSymbolItem>